{
    "plugins": {
        "SerpentHearthstoneGamePlugin": {
            "name": "SerpentHearthstoneGamePlugin",
            "version": "0.1.0",
            "files": [
                {
                    "path": "serpent_Hearthstone_game.py",
                    "pluggable": "Game"
                }
            ],
            "plugins": [],
            "libraries": [],
            "config": {
                "fps": 2
            }
        },
        "SerpentHearthstoneGameAgentPlugin": {
            "name": "SerpentHearthstoneGameAgentPlugin",
            "version": "0.1.0",
            "files": [
                {
                    "path": "serpent_Hearthstone_game_agent.py",
                    "pluggable": "GameAgent"
                }
            ],
            "plugins": [],
            "libraries": [],
            "config": {
                "frame_handler": "PLAY"
            }
        }
    }
}